.gitignore
.pre-commit-config.yaml
.pylintrc
.yamllint
LICENSE
README.md
Sword.cxx
Sword.h
Sword.py
markupcallback.h
mypy.ini
pyproject.toml
rendercallback.h
searcher.h
setup.cfg
setup.py
tox.ini
.github/labels.yml
.github/release-drafter.yml
.github/workflows/release-drafter.yml
.github/workflows/tox.yml
libsword.egg-info/PKG-INFO
libsword.egg-info/SOURCES.txt
libsword.egg-info/dependency_links.txt
libsword.egg-info/not-zip-safe
libsword.egg-info/top_level.txt
tests/test_something.py